{
    "buyHistory": [
        {
            "date": "2004-01-21",
            "Pay": 1000,
            "StockPrice": "1600.430054",
            "stockBuy": 0.6248320552970571,
            "accumulateResult": {
                "resProfitPerYear": 0,
                "resProfitTotal": 0,
                "duration": 0.031050228310502286,
                "stockTotal": 0.6248320552970571,
                "inputAmount": 1000,
                "outputAmount": 1000,
                "profitAmount": 0
            }
        },
        {
            "date": "2004-03-03",
            "Pay": 1000,
            "StockPrice": "1686.963989",
            "stockBuy": 0.5927808812284018,
            "accumulateResult": {
                "resProfitPerYear": 18.501796319561326,
                "resProfitTotal": 2.7034588229496004,
                "duration": 0.14611872146118723,
                "stockTotal": 1.2176129365254589,
                "inputAmount": 2000,
                "outputAmount": 2054.069176458992,
                "profitAmount": 54.06917645899193
            }
        },
        {
            "date": "2004-04-14",
            "Pay": 1000,
            "StockPrice": "1714.526001",
            "stockBuy": 0.5832515805632277,
            "accumulateResult": {
                "resProfitPerYear": 11.183426283847705,
                "resProfitTotal": 2.920967960895382,
                "duration": 0.2611872146118721,
                "stockTotal": 1.8008645170886866,
                "inputAmount": 3000,
                "outputAmount": 3087.6290388268617,
                "profitAmount": 87.62903882686169
            }
        },
        {
            "date": "2004-05-26",
            "Pay": 1000,
            "StockPrice": "1515.156006",
            "stockBuy": 0.6599980437921982,
            "accumulateResult": {
                "resProfitPerYear": -18.033567686903027,
                "resProfitTotal": -6.785232773519678,
                "duration": 0.3762557077625571,
                "stockTotal": 2.4608625608808845,
                "inputAmount": 4000,
                "outputAmount": 3728.5906890592128,
                "profitAmount": -271.40931094078724
            }
        },
        {
            "date": "2004-07-07",
            "Pay": 1000,
            "StockPrice": "1448.949951",
            "stockBuy": 0.6901549631233604,
            "accumulateResult": {
                "resProfitPerYear": -17.680110696220424,
                "resProfitTotal": -8.686666259878162,
                "duration": 0.491324200913242,
                "stockTotal": 3.151017524004245,
                "inputAmount": 5000,
                "outputAmount": 4565.666687006092,
                "profitAmount": -434.3333129939083
            }
        },
        {
            "date": "2004-08-18",
            "Pay": 1000,
            "StockPrice": "1359.870972",
            "stockBuy": 0.7353638842141562,
            "accumulateResult": {
                "resProfitPerYear": -19.652356848479656,
                "resProfitTotal": -11.917045614055244,
                "duration": 0.6063926940639269,
                "stockTotal": 3.886381408218401,
                "inputAmount": 6000,
                "outputAmount": 5284.977263156686,
                "profitAmount": -715.0227368433143
            }
        },
        {
            "date": "2004-09-29",
            "Pay": 1000,
            "StockPrice": "1436.706055",
            "stockBuy": 0.6960366015858407,
            "accumulateResult": {
                "resProfitPerYear": -8.245415319288428,
                "resProfitTotal": -5.948747125331377,
                "duration": 0.7214611872146118,
                "stockTotal": 4.5824180098042415,
                "inputAmount": 7000,
                "outputAmount": 6583.587701226804,
                "profitAmount": -416.4122987731962
            }
        },
        {
            "date": "2004-11-10",
            "Pay": 1000,
            "StockPrice": "1310.318970",
            "stockBuy": 0.7631729547500942,
            "accumulateResult": {
                "resProfitPerYear": -14.876500748441895,
                "resProfitTotal": -12.444634416048196,
                "duration": 0.8365296803652967,
                "stockTotal": 5.345590964554336,
                "inputAmount": 8000,
                "outputAmount": 7004.429246716144,
                "profitAmount": -995.570753283856
            }
        },
        {
            "date": "2004-12-22",
            "Pay": 1000,
            "StockPrice": "1277.182983",
            "stockBuy": 0.7829731630553678,
            "accumulateResult": {
                "resProfitPerYear": -13.692779842844416,
                "resProfitTotal": -13.030024288807196,
                "duration": 0.9515981735159816,
                "stockTotal": 6.128564127609703,
                "inputAmount": 9000,
                "outputAmount": 7827.297814007353,
                "profitAmount": -1172.7021859926472
            }
        },
        {
            "date": "2005-02-02",
            "Pay": 1000,
            "StockPrice": "1189.501953",
            "stockBuy": 0.8406879849822323,
            "accumulateResult": {
                "resProfitPerYear": -16.031821885523584,
                "resProfitTotal": -17.100610011225157,
                "duration": 1.0666666666666667,
                "stockTotal": 6.969252112591936,
                "inputAmount": 10000,
                "outputAmount": 8289.938998877484,
                "profitAmount": -1710.0610011225162
            }
        },
        {
            "date": "2005-03-16",
            "Pay": 1000,
            "StockPrice": "1267.052002",
            "stockBuy": 0.7892335897986293,
            "accumulateResult": {
                "resProfitPerYear": -8.997517903160986,
                "resProfitTotal": -10.63268325725143,
                "duration": 1.1817351598173516,
                "stockTotal": 7.758485702390566,
                "inputAmount": 11000,
                "outputAmount": 9830.404841702342,
                "profitAmount": -1169.5951582976577
            }
        },
        {
            "date": "2005-04-27",
            "Pay": 1000,
            "StockPrice": "1165.098999",
            "stockBuy": 0.8582961626937249,
            "accumulateResult": {
                "resProfitPerYear": -12.598900830140202,
                "resProfitTotal": -16.33830061990784,
                "duration": 1.2968036529680365,
                "stockTotal": 8.61678186508429,
                "inputAmount": 12000,
                "outputAmount": 10039.40392561106,
                "profitAmount": -1960.596074388941
            }
        },
        {
            "date": "2005-06-08",
            "Pay": 1000,
            "StockPrice": "1044.178955",
            "stockBuy": 0.9576902457299572,
            "accumulateResult": {
                "resProfitPerYear": -16.358736191339442,
                "resProfitTotal": -23.09644397425642,
                "duration": 1.4118721461187216,
                "stockTotal": 9.574472110814247,
                "inputAmount": 13000,
                "outputAmount": 9997.462283346666,
                "profitAmount": -3002.5377166533344
            }
        },
        {
            "date": "2005-07-20",
            "Pay": 1000,
            "StockPrice": "1013.984009",
            "stockBuy": 0.9862088466130831,
            "accumulateResult": {
                "resProfitPerYear": -15.397915377625491,
                "resProfitTotal": -23.511702750127693,
                "duration": 1.5269406392694065,
                "stockTotal": 10.56068095742733,
                "inputAmount": 14000,
                "outputAmount": 10708.361614982123,
                "profitAmount": -3291.638385017877
            }
        },
        {
            "date": "2005-08-31",
            "Pay": 1000,
            "StockPrice": "1145.812988",
            "stockBuy": 0.8727427690844085,
            "accumulateResult": {
                "resProfitPerYear": -7.711831233061779,
                "resProfitTotal": -12.662897312369935,
                "duration": 1.6420091324200914,
                "stockTotal": 11.433423726511739,
                "inputAmount": 15000,
                "outputAmount": 13100.56540314451,
                "profitAmount": -1899.4345968554899
            }
        },
        {
            "date": "2005-10-12",
            "Pay": 1000,
            "StockPrice": "1157.484985",
            "stockBuy": 0.863942092518807,
            "accumulateResult": {
                "resProfitPerYear": -6.281679319824606,
                "resProfitTotal": -11.037398183874469,
                "duration": 1.7570776255707763,
                "stockTotal": 12.297365819030546,
                "inputAmount": 16000,
                "outputAmount": 14234.016290580084,
                "profitAmount": -1765.9837094199156
            }
        },
        {
            "date": "2005-11-23",
            "Pay": 1000,
            "StockPrice": "1096.560059",
            "stockBuy": 0.9119427538806609,
            "accumulateResult": {
                "resProfitPerYear": -7.90285163292257,
                "resProfitTotal": -14.795293011407551,
                "duration": 1.8721461187214612,
                "stockTotal": 13.209308572911207,
                "inputAmount": 17000,
                "outputAmount": 14484.800188060717,
                "profitAmount": -2515.199811939283
            }
        },
        {
            "date": "2006-01-06",
            "Pay": 1000,
            "StockPrice": "1198.811035",
            "stockBuy": 0.8341598223609946,
            "accumulateResult": {
                "resProfitPerYear": -3.2466797899250706,
                "resProfitTotal": -6.469639544855255,
                "duration": 1.9926940639269408,
                "stockTotal": 14.043468395272201,
                "inputAmount": 18000,
                "outputAmount": 16835.464881926055,
                "profitAmount": -1164.5351180739453
            }
        },
        {
            "date": "2006-02-28",
            "Pay": 1000,
            "StockPrice": "1294.807007",
            "stockBuy": 0.772315869927942,
            "accumulateResult": {
                "resProfitPerYear": 0.4519469917393275,
                "resProfitTotal": 0.966217267271019,
                "duration": 2.1378995433789956,
                "stockTotal": 14.815784265200143,
                "inputAmount": 19000,
                "outputAmount": 19183.581280781495,
                "profitAmount": 183.58128078149457
            }
        },
        {
            "date": "2006-04-11",
            "Pay": 1000,
            "StockPrice": "1360.978027",
            "stockBuy": 0.7347657200640462,
            "accumulateResult": {
                "resProfitPerYear": 2.5831632292098985,
                "resProfitTotal": 5.819784188548693,
                "duration": 2.2529680365296803,
                "stockTotal": 15.55054998526419,
                "inputAmount": 20000,
                "outputAmount": 21163.95683770974,
                "profitAmount": 1163.9568377097385
            }
        },
        {
            "date": "2006-05-30",
            "Pay": 1000,
            "StockPrice": "1654.979980",
            "stockBuy": 0.6042369165094069,
            "accumulateResult": {
                "resProfitPerYear": 11.441604819185473,
                "resProfitTotal": 27.313566207626327,
                "duration": 2.387214611872146,
                "stockTotal": 16.154786901773598,
                "inputAmount": 21000,
                "outputAmount": 26735.84890360153,
                "profitAmount": 5735.848903601531
            }
        }
    ],
    "resProfitPerYear": 11.441604819185473,
    "resProfitTotal": 27.313566207626327,
    "duration": 2.387214611872146,
    "stockTotal": 16.154786901773598,
    "startPrice": "1449.567017",
    "endPrice": "1654.979980",
    "inputAmount": 21000,
    "outputAmount": 26735.84890360153,
    "profitAmount": 5735.848903601531,
    "startDate": "2004-1-10",
    "amountPerCycle": 1000,
    "cycleDuration": 30,
    "targetProfitPerYear": 10,
    "stockName": "SSE50_from_1997",
    "endDate": "2006-05-30",
    "succeed": true
}