{
    "buyHistory": [
        {
            "date": "2008-08-07",
            "Pay": 1000,
            "StockPrice": "2717.501953",
            "stockBuy": 0.36798501612705187,
            "accumulateResult": {
                "resProfitPerYear": -2.481008595846013e-13,
                "resProfitTotal": -1.1102230246251565e-14,
                "duration": 0.04474885844748858,
                "stockTotal": 0.36798501612705187,
                "inputAmount": 1000,
                "outputAmount": 999.9999999999999,
                "profitAmount": -1.1368683772161603e-13
            }
        },
        {
            "date": "2008-09-19",
            "Pay": 1000,
            "StockPrice": "2067.643066",
            "stockBuy": 0.48364247023281914,
            "accumulateResult": {
                "resProfitPerYear": -73.55518950821308,
                "resProfitTotal": -11.956916650650163,
                "duration": 0.16255707762557078,
                "stockTotal": 0.851627486359871,
                "inputAmount": 2000,
                "outputAmount": 1760.8616669869969,
                "profitAmount": -239.13833301300315
            }
        },
        {
            "date": "2008-11-07",
            "Pay": 1000,
            "StockPrice": "1686.524048",
            "stockBuy": 0.5929355120585864,
            "accumulateResult": {
                "resProfitPerYear": -63.30894276167517,
                "resProfitTotal": -18.790325477209525,
                "duration": 0.2968036529680365,
                "stockTotal": 1.4445629984184574,
                "inputAmount": 3000,
                "outputAmount": 2436.2902356837144,
                "profitAmount": -563.7097643162856
            }
        },
        {
            "date": "2008-12-19",
            "Pay": 1000,
            "StockPrice": "2006.208008",
            "stockBuy": 0.4984528005133952,
            "accumulateResult": {
                "resProfitPerYear": -6.185544802720475,
                "resProfitTotal": -2.547653612809986,
                "duration": 0.41187214611872147,
                "stockTotal": 1.9430157989318526,
                "inputAmount": 4000,
                "outputAmount": 3898.0938554876006,
                "profitAmount": -101.90614451239935
            }
        },
        {
            "date": "2009-02-10",
            "Pay": 1000,
            "StockPrice": "2218.489014",
            "stockBuy": 0.4507572467969859,
            "accumulateResult": {
                "resProfitPerYear": 11.149584535568161,
                "resProfitTotal": 6.211184079174958,
                "duration": 0.5570776255707763,
                "stockTotal": 2.3937730457288384,
                "inputAmount": 5000,
                "outputAmount": 5310.559203958748,
                "profitAmount": 310.5592039587482
            }
        },
        {
            "date": "2009-03-24",
            "Pay": 1000,
            "StockPrice": "2359.678955",
            "stockBuy": 0.4237864637818919,
            "accumulateResult": {
                "resProfitPerYear": 16.081222544442653,
                "resProfitTotal": 10.808931317543191,
                "duration": 0.6721461187214612,
                "stockTotal": 2.81755950951073,
                "inputAmount": 6000,
                "outputAmount": 6648.535879052592,
                "profitAmount": 648.5358790525916
            }
        },
        {
            "date": "2009-05-07",
            "Pay": 1000,
            "StockPrice": "2612.123047",
            "stockBuy": 0.3828303575317752,
            "accumulateResult": {
                "resProfitPerYear": 24.50616003193314,
                "resProfitTotal": 19.425887586957046,
                "duration": 0.7926940639269406,
                "stockTotal": 3.2003898670425053,
                "inputAmount": 7000,
                "outputAmount": 8359.812131086994,
                "profitAmount": 1359.8121310869938
            }
        },
        {
            "date": "2009-06-22",
            "Pay": 1000,
            "StockPrice": "2900.572021",
            "stockBuy": 0.3447595828547089,
            "accumulateResult": {
                "resProfitPerYear": 31.06166287991753,
                "resProfitTotal": 28.537016307942498,
                "duration": 0.9187214611872145,
                "stockTotal": 3.545149449897214,
                "inputAmount": 8000,
                "outputAmount": 10282.9613046354,
                "profitAmount": 2282.9613046354007
            }
        },
        {
            "date": "2009-08-03",
            "Pay": 1000,
            "StockPrice": "3429.693115",
            "stockBuy": 0.2915712766330115,
            "accumulateResult": {
                "resProfitPerYear": 44.69825532640922,
                "resProfitTotal": 46.208607332872354,
                "duration": 1.0337899543378994,
                "stockTotal": 3.8367207265302254,
                "inputAmount": 9000,
                "outputAmount": 13158.774659958512,
                "profitAmount": 4158.774659958512
            }
        }
    ],
    "resProfitPerYear": 44.69825532640922,
    "resProfitTotal": 46.208607332872354,
    "duration": 1.0337899543378994,
    "stockTotal": 3.8367207265302254,
    "startPrice": "2904.093994",
    "endPrice": "3429.693115",
    "inputAmount": 9000,
    "outputAmount": 13158.774659958512,
    "profitAmount": 4158.774659958512,
    "startDate": "2008-7-22",
    "amountPerCycle": 1000,
    "cycleDuration": 30,
    "targetProfitPerYear": 10,
    "stockName": "SSE50_from_1997",
    "endDate": "2009-08-03",
    "succeed": true
}